bloodhound_opengraph-1.0.1.dist-info/licenses/LICENSE
opengraph/__init__.py
opengraph/core.py
bloodhound_opengraph-1.0.1.dist-info/METADATA
bloodhound_opengraph-1.0.1.dist-info/WHEEL
bloodhound_opengraph-1.0.1.dist-info/top_level.txt
bloodhound_opengraph-1.0.1.dist-info/RECORD
