Metadata-Version: 2.4
Name: bloodhound-opengraph
Version: 1.0.1
Summary: A Python library for creating BloodHound OpenGraph JSON data
Home-page: https://github.com/rookuu/bloodhound-opengraph
Author: Luke Roberts
Author-email: Luke Roberts <rookuu@github.com>
Project-URL: Homepage, https://github.com/rookuu/bloodhound-opengraph
Project-URL: Documentation, https://github.com/rookuu/bloodhound-opengraph/blob/main/README.md
Project-URL: Repository, https://github.com/rookuu/bloodhound-opengraph
Project-URL: Bug Tracker, https://github.com/rookuu/bloodhound-opengraph/issues
Keywords: bloodhound,opengraph,security,graph,json
Classifier: Development Status :: 4 - Beta
Classifier: Intended Audience :: Developers
Classifier: Intended Audience :: System Administrators
Classifier: License :: OSI Approved :: MIT License
Classifier: Operating System :: OS Independent
Classifier: Programming Language :: Python :: 3
Classifier: Programming Language :: Python :: 3.8
Classifier: Programming Language :: Python :: 3.9
Classifier: Programming Language :: Python :: 3.10
Classifier: Programming Language :: Python :: 3.11
Classifier: Programming Language :: Python :: 3.12
Classifier: Topic :: Security
Classifier: Topic :: System :: Systems Administration
Classifier: Topic :: Software Development :: Libraries :: Python Modules
Classifier: Typing :: Typed
Requires-Python: >=3.8
License-File: LICENSE
Provides-Extra: dev
Requires-Dist: pytest>=7.0.0; extra == "dev"
Requires-Dist: pytest-cov>=4.0.0; extra == "dev"
Requires-Dist: pytest-mock>=3.10.0; extra == "dev"
Requires-Dist: pytest-xdist>=3.0.0; extra == "dev"
Requires-Dist: coverage>=6.0.0; extra == "dev"
Dynamic: author
Dynamic: home-page
Dynamic: license-file
Dynamic: requires-python
